bw_projects/__init__.py
bw_projects/config.py
bw_projects/core.py
bw_projects/errors.py
bw_projects/helpers.py
bw_projects/model.py
bw_projects-2.1.0.dist-info/LICENSE
bw_projects-2.1.0.dist-info/METADATA
bw_projects-2.1.0.dist-info/WHEEL
bw_projects-2.1.0.dist-info/top_level.txt
bw_projects-2.1.0.dist-info/RECORD
