Metadata-Version: 2.1
Name: bw-projects
Version: 2.1.0
Summary: This is a library to manage subdirectories.
Home-page: https://github.com/brightway-lca/brightway-projects
Author: Shantanu
Author-email: <baali@muse-amuse.in>
Maintainer: Shantanu
Maintainer-email: <baali@muse-amuse.in>
License: BSD
Project-URL: source, https://github.com/brightway-lca/brightway-projects
Project-URL: homepage, https://github.com/brightway-lca/brightway-projects
Project-URL: tracker, https://github.com/brightway-lca/brightway-projects/issues
Keywords: "brightway","development"
Platform: any
Classifier: Development Status :: 4 - Beta
Classifier: Programming Language :: Python
Classifier: Programming Language :: Python :: 3
Classifier: Programming Language :: Python :: 3.9
Classifier: Programming Language :: Python :: 3.10
Classifier: Programming Language :: Python :: 3.11
Requires-Python: >=3.9
License-File: LICENSE
Requires-Dist: platformdirs ==3.5.0
Requires-Dist: peewee >=3.9.4
Requires-Dist: python-slugify ==8.0.1
Provides-Extra: dev
Requires-Dist: pre-commit ; extra == 'dev'
Requires-Dist: pylint ; extra == 'dev'
Provides-Extra: docs
Requires-Dist: sphinx ; extra == 'docs'
Requires-Dist: myst-parser ; extra == 'docs'
Requires-Dist: furo ; extra == 'docs'
Provides-Extra: testing
Requires-Dist: setuptools ; extra == 'testing'
Requires-Dist: pytest ; extra == 'testing'
Requires-Dist: pytest-cov ; extra == 'testing'
